Workbook

Sheet Employee_Info
A1: Emp_ID | B1: Gender | C1: Department | D1: Role | E1: Experience | F1: City | G1: Metro_Type | H1: Join_Date
A2: E1 | B2: Male | C2: Operations | D2: Junior | E2: 7 | F2: Lucknow | G2: Non-Metro | H2: 43459
A3: E2 | B3: Female | C3: Sales | D3: Senior | E3: 14 | F3: Delhi | G3: Metro | H3: 44206
A4: E3 | B4: Male | C4: Operations | D4: Junior | E4: 8 | F4: Jaipur | G4: Non-Metro | H4: 42452
A5: E4 | B5: Female | C5: HR | D5: Junior | E5: 11 | F5: Pune | G5: Non-Metro | H5: 45247
A6: E5 | B6: Male | C6: IT | D6: Junior | E6: 5 | F6: Delhi | G6: Metro | H6: 45546
A7: E6 | B7: Female | C7: Sales | D7: Junior | E7: 2 | F7: Mumbai | G7: Metro | H7: 43575
A8: E7 | B8: Female | C8: HR | D8: Mid | E8: 11 | F8: Mumbai | G8: Metro | H8: 43170
A9: E8 | B9: Male | C9: Finance | D9: Mid | E9: 3 | F9: Jaipur | G9: Non-Metro | H9: 43882
A10: E9 | B10: Female | C10: Finance | D10: Senior | E10: 10 | F10: Indore | G10: Non-Metro | H10: 42262
A11: E10 | B11: Male | C11: Sales | D11: Mid | E11: 6 | F11: Mumbai | G11: Metro | H11: 44856
A12: E11 | B12: Female | C12: HR | D12: Junior | E12: 6 | F12: Pune | G12: Non-Metro | H12: 44713
A13: E12 | B13: Male | C13: IT | D13: Mid | E13: 7 | F13: Pune | G13: Non-Metro | H13: 43492
... A901: E900 | B901: Female | C901: Sales | D901: Mid | E901: 13 | F901: Indore | G901: Non-Metro | H901: 42577

Sheet Final_Payroll
A1: Emp_ID | B1: Dept | C1: Role | D1: Gender | E1: Exp | F1: City | G1: Gross | H1: Deductions | I1: Net | J1: Overtime_Pay | K1: Base_Increment_% (Next year) | L1: Performance_Adjustment_% | M1: Total_Increment_% | N1: Predicted_CTC
A2: E1 | B2: Operations | C2: Junior | D2: Male | E2: 7 | F2: Lucknow | G2: =Earnings!G2 -> 539814.46 | H2: =Deductions!B2+Deductions!C2+Deductions!D2+Tax!D2 -> 4158.8667 | I2: =G2-H2+J2 -> 535655.59 | J2: =Overtime!D2 -> 0 | K2: =IF(C2="Junior",0.06,IF(C2="Mid",0.08,IF(C2="Senior",0.1,IF(C2="Manager",0.12,0)))) -> 0.06 | L2: =IF(Performance!E2<=1.5,0.01,IF(Performance!E2<=2,0.02,IF(Performance!E2<=3,0.03,""))) -> 0.01 | M2: =K2+L2 -> 0.07 | N2: =Earnings!B2*(1+M2) -> 606724.24
A3: E2 | B3: Sales | C3: Senior | D3: Female | E3: 19.6 | F3: Delhi | G3: =Earnings!G3 -> 1295462.7 | H3: =Deductions!B3+Deductions!C3+Deductions!D3+Tax!D3 -> 20474.505 | I3: =G3-H3+J3 -> 1560752.1 | J3: =Overtime!D3 -> 285763.84 | K3: =IF(C3="Junior",0.06,IF(C3="Mid",0.08,IF(C3="Senior",0.1,IF(C3="Manager",0.12,0)))) -> 0.1 | L3: =IF(Performance!E3<=1.5,0.01,IF(Performance!E3<=2,0.02,IF(Performance!E3<=3,0.03,""))) -> 0.03 | M3: =K3+L3 -> 0.13 | N3: =Earnings!B3*(1+M3) -> 1537681.6
A4: E3 | B4: Operations | C4: Junior | D4: Male | E4: 8 | F4: Jaipur | G4: =Earnings!G4 -> 616474.26 | H4: =Deductions!B4+Deductions!C4+Deductions!D4+Tax!D4 -> 5500.95 | I4: =G4-H4+J4 -> 630400.02 | J4: =Overtime!D4 -> 19426.71 | K4: =IF(C4="Junior",0.06,IF(C4="Mid",0.08,IF(C4="Senior",0.1,IF(C4="Manager",0.12,0)))) -> 0.06 | L4: =IF(Performance!E4<=1.5,0.01,IF(Performance!E4<=2,0.02,IF(Performance!E4<=3,0.03,""))) -> 0.01 | M4: =K4+L4 -> 0.07 | N4: =Earnings!B4*(1+M4) -> 692885.99
A5: E4 | B5: HR | C5: Junior | D5: Female | E5: 11 | F5: Pune | G5: =Earnings!G5 -> 672030.7 | H5: =Deductions!B5+Deductions!C5+Deductions!D5+Tax!D5 -> 6473.5767 | I5: =G5-H5+J5 -> 665557.12 | J5: =Overtime!D5 -> 0 | K5: =IF(C5="Junior",0.06,IF(C5="Mid",0.08,IF(C5="Senior",0.1,IF(C5="Manager",0.12,0)))) -> 0.06 | L5: =IF(Performance!E5<=1.5,0.01,IF(Performance!E5<=2,0.02,IF(Performance!E5<=3,0.03,""))) -> 0.01 | M5: =K5+L5 -> 0.07 | N5: =Earnings!B5*(1+M5) -> 755328.62
A6: E5 | B6: IT | C6: Junior | D6: Male | E6: 5 | F6: Delhi | G6: =Earnings!G6 -> 952611.18 | H6: =Deductions!B6+Deductions!C6+Deductions!D6+Tax!D6 -> 11391.05 | I6: =G6-H6+J6 -> 996255.44 | J6: =Overtime!D6 -> 55035.31 | K6: =IF(C6="Junior",0.06,IF(C6="Mid",0.08,IF(C6="Senior",0.1,IF(C6="Manager",0.12,0)))) -> 0.06 | L6: =IF(Performance!E6<=1.5,0.01,IF(Performance!E6<=2,0.02,IF(Performance!E6<=3,0.03,""))) -> 0.02 | M6: =K6+L6 -> 0.08 | N6: =Earnings!B6*(1+M6) -> 1080693.4
A7: E6 | B7: Sales | C7: Junior | D7: Female | E7: 2 | F7: Mumbai | G7: =Earnings!G7 -> 489313.86 | H7: =Deductions!B7+Deductions!C7+Deductions!D7+Tax!D7 -> 3274.7525 | I7: =G7-H7+J7 -> 486039.11 | J7: =Overtime!D7 -> 0 | K7: =IF(C7="Junior",0.06,IF(C7="Mid",0.08,IF(C7="Senior",0.1,IF(C7="Manager",0.12,0)))) -> 0.06 | L7: =IF(Performance!E7<=1.5,0.01,IF(Performance!E7<=2,0.02,IF(Performance!E7<=3,0.03,""))) -> 0.03 | M7: =K7+L7 -> 0.09 | N7: =Earnings!B7*(1+M7) -> 560243.81
A8: E7 | B8: HR | C8: Mid | D8: Female | E8: 13.2 | F8: Mumbai | G8: =Earnings!G8 -> 1030780.5 | H8: =Deductions!B8+Deductions!C8+Deductions!D8+Tax!D8 -> 13483.816 | I8: =G8-H8+J8 -> 1017296.7 | J8: =Overtime!D8 -> 0 | K8: =IF(C8="Junior",0.06,IF(C8="Mid",0.08,IF(C8="Senior",0.1,IF(C8="Manager",0.12,0)))) -> 0.08 | L8: =IF(Performance!E8<=1.5,0.01,IF(Performance!E8<=2,0.02,IF(Performance!E8<=3,0.03,""))) -> 0.01 | M8: =K8+L8 -> 0.09 | N8: =Earnings!B8*(1+M8) -> 1180200.4
A9: E8 | B9: Finance | C9: Mid | D9: Male | E9: 3.6 | F9: Jaipur | G9: =Earnings!G9 -> 1237062.7 | H9: =Deductions!B9+Deductions!C9+Deductions!D9+Tax!D9 -> 18900.89 | I9: =G9-H9+J9 -> 1358500.8 | J9: =Overtime!D9 -> 140339.04 | K9: =IF(C9="Junior",0.06,IF(C9="Mid",0.08,IF(C9="Senior",0.1,IF(C9="Manager",0.12,0)))) -> 0.08 | L9: =IF(Performance!E9<=1.5,0.01,IF(Performance!E9<=2,0.02,IF(Performance!E9<=3,0.03,""))) -> 0.01 | M9: =K9+L9 -> 0.09 | N9: =Earnings!B9*(1+M9) -> 1416384.8
A10: E9 | B10: Finance | C10: Senior | D10: Female | E10: 14 | F10: Indore | G10: =Earnings!G10 -> 1634425.2 | H10: =Deductions!B10+Deductions!C10+Deductions!D10+Tax!D10 -> 29375.829 | I10: =G10-H10+J10 -> 1605049.3 | J10: =Overtime!D10 -> 0 | K10: =IF(C10="Junior",0.06,IF(C10="Mid",0.08,IF(C10="Senior",0.1,IF(C10="Manager",0.12,0)))) -> 0.1 | L10: =IF(Performance!E10<=1.5,0.01,IF(Performance!E10<=2,0.02,IF(Performance!E10<=3,0.03,""))) -> 0.01 | M10: =K10+L10 -> 0.11 | N10: =Earnings!B10*(1+M10) -> 1905684.8
A11: E10 | B11: Sales | C11: Mid | D11: Male | E11: 7.2 | F11: Mumbai | G11: =Earnings!G11 -> 1022572.5 | H11: =Deductions!B11+Deductions!C11+Deductions!D11+Tax!D11 -> 13268.27 | I11: =G11-H11+J11 -> 1183313.4 | J11: =Overtime!D11 -> 174009.19 | K11: =IF(C11="Junior",0.06,IF(C11="Mid",0.08,IF(C11="Senior",0.1,IF(C11="Manager",0.12,0)))) -> 0.08 | L11: =IF(Performance!E11<=1.5,0.01,IF(Performance!E11<=2,0.02,IF(Performance!E11<=3,0.03,""))) -> 0.03 | M11: =K11+L11 -> 0.11 | N11: =Earnings!B11*(1+M11) -> 1192285.2
A12: E11 | B12: HR | C12: Junior | D12: Female | E12: 6 | F12: Pune | G12: =Earnings!G12 -> 535136.19 | H12: =Deductions!B12+Deductions!C12+Deductions!D12+Tax!D12 -> 4076.9642 | I12: =G12-H12+J12 -> 531059.23 | J12: =Overtime!D12 -> 0 | K12: =IF(C12="Junior",0.06,IF(C12="Mid",0.08,IF(C12="Senior",0.1,IF(C12="Manager",0.12,0)))) -> 0.06 | L12: =IF(Performance!E12<=1.5,0.01,IF(Performance!E12<=2,0.02,IF(Performance!E12<=3,0.03,""))) -> 0.01 | M12: =K12+L12 -> 0.07 | N12: =Earnings!B12*(1+M12) -> 601466.1
A13: E12 | B13: IT | C13: Mid | D13: Male | E13: 8.4 | F13: Pune | G13: =Earnings!G13 -> 1143660.1 | H13: =Deductions!B13+Deductions!C13+Deductions!D13+Tax!D13 -> 16448.09 | I13: =G13-H13+J13 -> 1213707.3 | J13: =Overtime!D13 -> 86495.299 | K13: =IF(C13="Junior",0.06,IF(C13="Mid",0.08,IF(C13="Senior",0.1,IF(C13="Manager",0.12,0)))) -> 0.08 | L13: =IF(Performance!E13<=1.5,0.01,IF(Performance!E13<=2,0.02,IF(Performance!E13<=3,0.03,""))) -> 0.02 | M13: =K13+L13 -> 0.1 | N13: =Earnings!B13*(1+M13) -> 1321456
... A901: E900 | B901: Sales | C901: Mid | D901: Female | E901: 15.6 | F901: Indore | G901: =Earnings!G901 -> 1051427.9 | H901: =Deductions!B901+Deductions!C901+Deductions!D901+Tax!D901 -> 12226.028 | I901: =G901-H901+J901 -> 1039201.9 | J901: =Overtime!D901 -> 0 | K901: =IF(C901="Junior",0.06,IF(C901="Mid",0.08,IF(C901="Senior",0.1,IF(C901="Manager",0.12,0)))) -> 0.08 | L901: =IF(Performance!E901<=1.5,0.01,IF(Performance!E901<=2,0.02,IF(Performance!E901<=3,0.03,""))) -> 0.03 | M901: =K901+L901 -> 0.11 | N901: =Earnings!B901*(1+M901) -> 1225929.6

Sheet Earnings
A1: Emp_ID | B1: CTC | C1: Basic | D1: HRA | E1: Allowance | F1: Bonus | G1: Gross
A2: E1 | B2: 567032 | C2: 226812.8 | D2: 113406.4 | E2: 142892.06 | F2: 56703.2 | G2: 539814.46
A3: E2 | B3: 1360780.2 | C3: 544312.08 | D3: 272156.04 | E3: 342916.61 | F3: 136078.02 | G3: 1295462.7
A4: E3 | B4: 647557 | C4: 259022.8 | D4: 129511.4 | E4: 163184.36 | F4: 64755.7 | G4: 616474.26
A5: E4 | B5: 705914.6 | C5: 282365.84 | D5: 141182.92 | E5: 177890.48 | F5: 70591.46 | G5: 672030.7
A6: E5 | B6: 1000642 | C6: 400256.8 | D6: 200128.4 | E6: 252161.78 | F6: 100064.2 | G6: 952611.18
A7: E6 | B7: 513985.15 | C7: 205594.06 | D7: 102797.03 | E7: 129524.26 | F7: 51398.52 | G7: 489313.86
A8: E7 | B8: 1082752.6 | C8: 433101.05 | D8: 216550.52 | E8: 272853.66 | F8: 108275.26 | G8: 1030780.5
A9: E8 | B9: 1299435.6 | C9: 519774.24 | D9: 259887.12 | E9: 327457.77 | F9: 129943.56 | G9: 1237062.7
A10: E9 | B10: 1716833.2 | C10: 686733.26 | D10: 343366.63 | E10: 432641.96 | F10: 171683.32 | G10: 1634425.2
A11: E10 | B11: 1074130.8 | C11: 429652.32 | D11: 214826.16 | E11: 270680.96 | F11: 107413.08 | G11: 1022572.5
A12: E11 | B12: 562117.85 | C12: 224847.14 | D12: 112423.57 | E12: 141653.7 | F12: 56211.79 | G12: 535136.19
A13: E12 | B13: 1201323.6 | C13: 480529.44 | D13: 240264.72 | E13: 302733.55 | F13: 120132.36 | G13: 1143660.1
... A901: E900 | B901: 1104441.1 | C901: 441776.45 | D901: 220888.22 | E901: 278319.16 | F901: 110444.11 | G901: 1051427.9

Sheet Deductions
A1: Emp_ID | B1: PF | C1: ESI | D1: PT
A2: E1 | B2: =MIN(0.12*Earnings!C3,1800) -> 1800 | C2: =IF([1]Earnings!G2<=21000,0.0075*[1]Earnings!G2,0) -> 0 | D2: 200
A3: E2 | B3: =MIN(0.12*Earnings!C4,1800) -> 1800 | C3: =IF([1]Earnings!G3<=21000,0.0075*[1]Earnings!G3,0) -> 0 | D3: 280
A4: E3 | B4: =MIN(0.12*Earnings!C5,1800) -> 1800 | C4: =IF([1]Earnings!G4<=21000,0.0075*[1]Earnings!G4,0) -> 0 | D4: 200
A5: E4 | B5: =MIN(0.12*Earnings!C6,1800) -> 1800 | C5: =IF([1]Earnings!G5<=21000,0.0075*[1]Earnings!G5,0) -> 0 | D5: 200
A6: E5 | B6: =MIN(0.12*Earnings!C7,1800) -> 1800 | C6: =IF([1]Earnings!G6<=21000,0.0075*[1]Earnings!G6,0) -> 0 | D6: 200
A7: E6 | B7: =MIN(0.12*Earnings!C8,1800) -> 1800 | C7: =IF([1]Earnings!G7<=21000,0.0075*[1]Earnings!G7,0) -> 0 | D7: 200
A8: E7 | B8: =MIN(0.12*Earnings!C9,1800) -> 1800 | C8: =IF([1]Earnings!G8<=21000,0.0075*[1]Earnings!G8,0) -> 0 | D8: 240
A9: E8 | B9: =MIN(0.12*Earnings!C10,1800) -> 1800 | C9: =IF([1]Earnings!G9<=21000,0.0075*[1]Earnings!G9,0) -> 0 | D9: 240
A10: E9 | B10: =MIN(0.12*Earnings!C11,1800) -> 1800 | C10: =IF([1]Earnings!G10<=21000,0.0075*[1]Earnings!G10,0) -> 0 | D10: 280
A11: E10 | B11: =MIN(0.12*Earnings!C12,1800) -> 1800 | C11: =IF([1]Earnings!G11<=21000,0.0075*[1]Earnings!G11,0) -> 0 | D11: 240
A12: E11 | B12: =MIN(0.12*Earnings!C13,1800) -> 1800 | C12: =IF([1]Earnings!G12<=21000,0.0075*[1]Earnings!G12,0) -> 0 | D12: 200
A13: E12 | B13: =MIN(0.12*Earnings!C14,1800) -> 1800 | C13: =IF([1]Earnings!G13<=21000,0.0075*[1]Earnings!G13,0) -> 0 | D13: 240
... A901: E900 | B901: =MIN(0.12*Earnings!C902,1800) -> 0 | C901: =IF([1]Earnings!G901<=21000,0.0075*[1]Earnings!G901,0) -> 0 | D901: 240

Sheet Tax
A1: Emp_ID | B1: Annual | C1: Tax | D1: Monthly_TDS
A2: E1 | B2: =Earnings!B2 -> 567032 | C2: =IF(B2<=250000,0,IF(B2<=500000,(B2-250000)*0.05,IF(B2<=1000000,12500+(B2-500000)*0.2,112500+(B2-1000000)*0.3))) -> 25906.4 | D2: =C2/12 -> 2158.8667
A3: E2 | B3: =Earnings!B3 -> 1360780.2 | C3: =IF(B3<=250000,0,IF(B3<=500000,(B3-250000)*0.05,IF(B3<=1000000,12500+(B3-500000)*0.2,112500+(B3-1000000)*0.3))) -> 220734.06 | D3: =C3/12 -> 18394.505
A4: E3 | B4: =Earnings!B4 -> 647557 | C4: =IF(B4<=250000,0,IF(B4<=500000,(B4-250000)*0.05,IF(B4<=1000000,12500+(B4-500000)*0.2,112500+(B4-1000000)*0.3))) -> 42011.4 | D4: =C4/12 -> 3500.95
A5: E4 | B5: =Earnings!B5 -> 705914.6 | C5: =IF(B5<=250000,0,IF(B5<=500000,(B5-250000)*0.05,IF(B5<=1000000,12500+(B5-500000)*0.2,112500+(B5-1000000)*0.3))) -> 53682.92 | D5: =C5/12 -> 4473.5767
A6: E5 | B6: =Earnings!B6 -> 1000642 | C6: =IF(B6<=250000,0,IF(B6<=500000,(B6-250000)*0.05,IF(B6<=1000000,12500+(B6-500000)*0.2,112500+(B6-1000000)*0.3))) -> 112692.6 | D6: =C6/12 -> 9391.05
A7: E6 | B7: =Earnings!B7 -> 513985.15 | C7: =IF(B7<=250000,0,IF(B7<=500000,(B7-250000)*0.05,IF(B7<=1000000,12500+(B7-500000)*0.2,112500+(B7-1000000)*0.3))) -> 15297.03 | D7: =C7/12 -> 1274.7525
A8: E7 | B8: =Earnings!B8 -> 1082752.6 | C8: =IF(B8<=250000,0,IF(B8<=500000,(B8-250000)*0.05,IF(B8<=1000000,12500+(B8-500000)*0.2,112500+(B8-1000000)*0.3))) -> 137325.79 | D8: =C8/12 -> 11443.816
A9: E8 | B9: =Earnings!B9 -> 1299435.6 | C9: =IF(B9<=250000,0,IF(B9<=500000,(B9-250000)*0.05,IF(B9<=1000000,12500+(B9-500000)*0.2,112500+(B9-1000000)*0.3))) -> 202330.68 | D9: =C9/12 -> 16860.89
A10: E9 | B10: =Earnings!B10 -> 1716833.2 | C10: =IF(B10<=250000,0,IF(B10<=500000,(B10-250000)*0.05,IF(B10<=1000000,12500+(B10-500000)*0.2,112500+(B10-1000000)*0.3))) -> 327549.95 | D10: =C10/12 -> 27295.829
A11: E10 | B11: =Earnings!B11 -> 1074130.8 | C11: =IF(B11<=250000,0,IF(B11<=500000,(B11-250000)*0.05,IF(B11<=1000000,12500+(B11-500000)*0.2,112500+(B11-1000000)*0.3))) -> 134739.24 | D11: =C11/12 -> 11228.27
A12: E11 | B12: =Earnings!B12 -> 562117.85 | C12: =IF(B12<=250000,0,IF(B12<=500000,(B12-250000)*0.05,IF(B12<=1000000,12500+(B12-500000)*0.2,112500+(B12-1000000)*0.3))) -> 24923.57 | D12: =C12/12 -> 2076.9642
A13: E12 | B13: =Earnings!B13 -> 1201323.6 | C13: =IF(B13<=250000,0,IF(B13<=500000,(B13-250000)*0.05,IF(B13<=1000000,12500+(B13-500000)*0.2,112500+(B13-1000000)*0.3))) -> 172897.08 | D13: =C13/12 -> 14408.09
... A901: E900 | B901: =Earnings!B901 -> 1104441.1 | C901: =IF(B901<=250000,0,IF(B901<=500000,(B901-250000)*0.05,IF(B901<=1000000,12500+(B901-500000)*0.2,112500+(B901-1000000)*0.3))) -> 143832.34 | D901: =C901/12 -> 11986.028

Sheet Overtime
A1: Emp_ID | B1: Overtime_Hours | C1: Hourly_Rate | D1: OT_Pay
A2: E1 | B2: 0 | C2: =Earnings!C2/160 -> 1417.58 | D2: =B2*C2*2 -> 0
A3: E2 | B3: 42 | C3: =Earnings!C3/160 -> 3401.9505 | D3: =B3*C3*2 -> 285763.84
A4: E3 | B4: 6 | C4: =Earnings!C4/160 -> 1618.8925 | D4: =B4*C4*2 -> 19426.71
A5: E4 | B5: 0 | C5: =Earnings!C5/160 -> 1764.7865 | D5: =B5*C5*2 -> 0
A6: E5 | B6: 11 | C6: =Earnings!C6/160 -> 2501.605 | D6: =B6*C6*2 -> 55035.31
A7: E6 | B7: 0 | C7: =Earnings!C7/160 -> 1284.9629 | D7: =B7*C7*2 -> 0
A8: E7 | B8: 0 | C8: =Earnings!C8/160 -> 2706.8816 | D8: =B8*C8*2 -> 0
A9: E8 | B9: 21.6 | C9: =Earnings!C9/160 -> 3248.589 | D9: =B9*C9*2 -> 140339.04
A10: E9 | B10: 0 | C10: =Earnings!C10/160 -> 4292.0829 | D10: =B10*C10*2 -> 0
A11: E10 | B11: 32.4 | C11: =Earnings!C11/160 -> 2685.327 | D11: =B11*C11*2 -> 174009.19
A12: E11 | B12: 0 | C12: =Earnings!C12/160 -> 1405.2946 | D12: =B12*C12*2 -> 0
A13: E12 | B13: 14.4 | C13: =Earnings!C13/160 -> 3003.309 | D13: =B13*C13*2 -> 86495.299
... A901: E900 | B901: 0 | C901: =Earnings!C901/160 -> 2761.1028 | D901: =B901*C901*2 -> 0

Sheet Performance
A1: Emp_ID | B1: Value_Generated | C1: Employer_Cost | D1: Net_Value | E1: ROI
A2: E1 | B2: =IF(Final_Payroll!B2="Sales",Earnings!B2*3, IF(Final_Payroll!B2="IT",Earnings!B2*2, IF(Final_Payroll!B2="Finance",Earnings!B2*1.5, IF(Final_Payroll!B2="HR",Earnings!B2*1.2, Earnings!B2*1.3)))) -> 737141.6 | C2: =Earnings!B2 + Deductions!B2 + Deductions!C2 + Overtime!D2 -> 568832 | D2: =B2-C2 -> 168309.6 | E2: =IF(C2=0,0,B2/C2) -> 1.2958863
A3: E2 | B3: =IF(Final_Payroll!B3="Sales",Earnings!B3*3, IF(Final_Payroll!B3="IT",Earnings!B3*2, IF(Final_Payroll!B3="Finance",Earnings!B3*1.5, IF(Final_Payroll!B3="HR",Earnings!B3*1.2, Earnings!B3*1.3)))) -> 4082340.6 | C3: =Earnings!B3 + Deductions!B3 + Deductions!C3 + Overtime!D3 -> 1648344 | D3: =B3-C3 -> 2433996.5 | E3: =IF(C3=0,0,B3/C3) -> 2.4766314
A4: E3 | B4: =IF(Final_Payroll!B4="Sales",Earnings!B4*3, IF(Final_Payroll!B4="IT",Earnings!B4*2, IF(Final_Payroll!B4="Finance",Earnings!B4*1.5, IF(Final_Payroll!B4="HR",Earnings!B4*1.2, Earnings!B4*1.3)))) -> 841824.1 | C4: =Earnings!B4 + Deductions!B4 + Deductions!C4 + Overtime!D4 -> 668783.71 | D4: =B4-C4 -> 173040.39 | E4: =IF(C4=0,0,B4/C4) -> 1.2587389
A5: E4 | B5: =IF(Final_Payroll!B5="Sales",Earnings!B5*3, IF(Final_Payroll!B5="IT",Earnings!B5*2, IF(Final_Payroll!B5="Finance",Earnings!B5*1.5, IF(Final_Payroll!B5="HR",Earnings!B5*1.2, Earnings!B5*1.3)))) -> 847097.52 | C5: =Earnings!B5 + Deductions!B5 + Deductions!C5 + Overtime!D5 -> 707714.6 | D5: =B5-C5 -> 139382.92 | E5: =IF(C5=0,0,B5/C5) -> 1.1969479
A6: E5 | B6: =IF(Final_Payroll!B6="Sales",Earnings!B6*3, IF(Final_Payroll!B6="IT",Earnings!B6*2, IF(Final_Payroll!B6="Finance",Earnings!B6*1.5, IF(Final_Payroll!B6="HR",Earnings!B6*1.2, Earnings!B6*1.3)))) -> 2001284 | C6: =Earnings!B6 + Deductions!B6 + Deductions!C6 + Overtime!D6 -> 1057477.3 | D6: =B6-C6 -> 943806.69 | E6: =IF(C6=0,0,B6/C6) -> 1.8925077
A7: E6 | B7: =IF(Final_Payroll!B7="Sales",Earnings!B7*3, IF(Final_Payroll!B7="IT",Earnings!B7*2, IF(Final_Payroll!B7="Finance",Earnings!B7*1.5, IF(Final_Payroll!B7="HR",Earnings!B7*1.2, Earnings!B7*1.3)))) -> 1541955.5 | C7: =Earnings!B7 + Deductions!B7 + Deductions!C7 + Overtime!D7 -> 515785.15 | D7: =B7-C7 -> 1026170.3 | E7: =IF(C7=0,0,B7/C7) -> 2.9895305
A8: E7 | B8: =IF(Final_Payroll!B8="Sales",Earnings!B8*3, IF(Final_Payroll!B8="IT",Earnings!B8*2, IF(Final_Payroll!B8="Finance",Earnings!B8*1.5, IF(Final_Payroll!B8="HR",Earnings!B8*1.2, Earnings!B8*1.3)))) -> 1299303.1 | C8: =Earnings!B8 + Deductions!B8 + Deductions!C8 + Overtime!D8 -> 1084552.6 | D8: =B8-C8 -> 214750.52 | E8: =IF(C8=0,0,B8/C8) -> 1.1980084
A9: E8 | B9: =IF(Final_Payroll!B9="Sales",Earnings!B9*3, IF(Final_Payroll!B9="IT",Earnings!B9*2, IF(Final_Payroll!B9="Finance",Earnings!B9*1.5, IF(Final_Payroll!B9="HR",Earnings!B9*1.2, Earnings!B9*1.3)))) -> 1949153.4 | C9: =Earnings!B9 + Deductions!B9 + Deductions!C9 + Overtime!D9 -> 1441574.6 | D9: =B9-C9 -> 507578.76 | E9: =IF(C9=0,0,B9/C9) -> 1.3521002
A10: E9 | B10: =IF(Final_Payroll!B10="Sales",Earnings!B10*3, IF(Final_Payroll!B10="IT",Earnings!B10*2, IF(Final_Payroll!B10="Finance",Earnings!B10*1.5, IF(Final_Payroll!B10="HR",Earnings!B10*1.2, Earnings!B10*1.3)))) -> 2575249.7 | C10: =Earnings!B10 + Deductions!B10 + Deductions!C10 + Overtime!D10 -> 1718633.2 | D10: =B10-C10 -> 856616.58 | E10: =IF(C10=0,0,B10/C10) -> 1.498429
A11: E10 | B11: =IF(Final_Payroll!B11="Sales",Earnings!B11*3, IF(Final_Payroll!B11="IT",Earnings!B11*2, IF(Final_Payroll!B11="Finance",Earnings!B11*1.5, IF(Final_Payroll!B11="HR",Earnings!B11*1.2, Earnings!B11*1.3)))) -> 3222392.4 | C11: =Earnings!B11 + Deductions!B11 + Deductions!C11 + Overtime!D11 -> 1249940 | D11: =B11-C11 -> 1972452.4 | E11: =IF(C11=0,0,B11/C11) -> 2.5780377
A12: E11 | B12: =IF(Final_Payroll!B12="Sales",Earnings!B12*3, IF(Final_Payroll!B12="IT",Earnings!B12*2, IF(Final_Payroll!B12="Finance",Earnings!B12*1.5, IF(Final_Payroll!B12="HR",Earnings!B12*1.2, Earnings!B12*1.3)))) -> 674541.42 | C12: =Earnings!B12 + Deductions!B12 + Deductions!C12 + Overtime!D12 -> 563917.85 | D12: =B12-C12 -> 110623.57 | E12: =IF(C12=0,0,B12/C12) -> 1.1961697
A13: E12 | B13: =IF(Final_Payroll!B13="Sales",Earnings!B13*3, IF(Final_Payroll!B13="IT",Earnings!B13*2, IF(Final_Payroll!B13="Finance",Earnings!B13*1.5, IF(Final_Payroll!B13="HR",Earnings!B13*1.2, Earnings!B13*1.3)))) -> 2402647.2 | C13: =Earnings!B13 + Deductions!B13 + Deductions!C13 + Overtime!D13 -> 1289618.9 | D13: =B13-C13 -> 1113028.3 | E13: =IF(C13=0,0,B13/C13) -> 1.8630676
... A901: E900 | B901: =IF(Final_Payroll!B901="Sales",Earnings!B901*3, IF(Final_Payroll!B901="IT",Earnings!B901*2, IF(Final_Payroll!B901="Finance",Earnings!B901*1.5, IF(Final_Payroll!B901="HR",Earnings!B901*1.2, Earnings!B901*1.3)))) -> 3313323.4 | C901: =Earnings!B901 + Deductions!B901 + Deductions!C901 + Overtime!D901 -> 1104441.1 | D901: =B901-C901 -> 2208882.2 | E901: =IF(C901=0,0,B901/C901) -> 3

Sheet Labour_Law_Rules
A1: Rule | B1: Details
A2: Dept Salary Bands | B2: IT highest, Ops lowest
A3: Gender Pay Gap | B3: Female ~5% lower
A4: Metro HRA | B4: 50% basic
A5: Non Metro HRA | B5: 40% basic
A6: PF | B6: 12% capped 1800
A7: ESI | B7: <=21000
A8: Tax Slabs | B8: 0-2.5L 0%, 2.5-5L 5%, 5-10L 20%, 10L+ 30%
A9: Overtime Rule | B9: 2x hourly wage for extra hours
A10: Hourly Rate Calculation | B10: Basic Salary / 160 hours per month
A11: --- Performance Analytics ---
A12: Value Generation Assumption | B12: Based on department multipliers (proxy model)
A13: Sales Multiplier | B13: ~3x CTC
A14: IT Multiplier | B14: ~2x CTC
A15: Finance Multiplier | B15: ~1.5x CTC
A16: HR Multiplier | B16: ~1.2x CTC
A17: Operations Multiplier | B17: ~1.3x CTC
A18: Employer Cost | B18: CTC + PF + ESI + Overtime
A19: Net Value | B19: Value Generated - Employer Cost
A20: ROI | B20: Value Generated / Employer Cost
A21: Note | B21: Actual employee value cannot be directly measured; proxies are used
